fc2_live_dl/FC2LiveDL.py
fc2_live_dl/__init__.py
fc2_live_dl/__main__.py
fc2_live_dl/autofc2.py
fc2_live_dl/fc2.py
fc2_live_dl/ffmpeg.py
fc2_live_dl/hls.py
fc2_live_dl/util.py
fc2_live_dl-2.2.0.dist-info/LICENSE
fc2_live_dl-2.2.0.dist-info/METADATA
fc2_live_dl-2.2.0.dist-info/WHEEL
fc2_live_dl-2.2.0.dist-info/entry_points.txt
fc2_live_dl-2.2.0.dist-info/top_level.txt
fc2_live_dl-2.2.0.dist-info/RECORD
