Metadata-Version: 2.1
Name: fc2-live-dl
Version: 2.2.0
Summary: Download live streams from FC2
Home-page: https://github.com/HoloArchivists/fc2-live-dl
Author: Hizkia Felix
Author-email: felix@hizkifw.me
Project-URL: Bug Tracker, https://github.com/HoloArchivists/fc2-live-dl/issues
Classifier: Development Status :: 5 - Production/Stable
Classifier: Environment :: Console
Classifier: License :: OSI Approved :: MIT License
Classifier: Natural Language :: English
Classifier: Operating System :: OS Independent
Classifier: Programming Language :: Python :: 3 :: Only
Classifier: Programming Language :: Python :: 3.8
Requires-Python: >=3.8
License-File: LICENSE
Requires-Dist: aiohttp (>=3.8.1)
Requires-Dist: aiodns (>=3.0.0)
Requires-Dist: apprise (>=1.4.5)
